{
  "secret_word": "forest",
  "weak_connections": [
    {
      "rank": 257,
      "word": "farm",
      "similarity": 0.53189207,
      "clue": "weak connection",
      "strength": "weak"
    },
    {
      "rank": 259,
      "word": "fore",
      "similarity": 0.52590808,
      "clue": "weak connection",
      "strength": "weak"
    },
    {
      "rank": 271,
      "word": "silvae",
      "similarity": 0.50630548,
      "clue": "weak connection",
      "strength": "weak"
    },
    {
      "rank": 273,
      "word": "yard",
      "similarity": 0.50362453,
      "clue": "weak connection",
      "strength": "weak"
    },
    {
      "rank": 280,
      "word": "folk",
      "similarity": 0.49618476,
      "clue": "weak connection",
      "strength": "weak"
    },
    {
      "rank": 286,
      "word": "foss",
      "similarity": 0.48692823,
      "clue": "weak connection",
      "strength": "weak"
    },
    {
      "rank": 291,
      "word": "environment",
      "similarity": 0.47906862,
      "clue": "weak connection",
      "strength": "weak"
    },
    {
      "rank": 301,
      "word": "fog",
      "similarity": 0.46826464,
      "clue": "weak connection",
      "strength": "weak"
    },
    {
      "rank": 354,
      "word": "ford",
      "similarity": 0.43603584,
      "clue": "weak connection",
      "strength": "weak"
    },
    {
      "rank": 357,
      "word": "treen",
      "similarity": 0.43572961,
      "clue": "weak connection",
      "strength": "weak"
    },
    {
      "rank": 360,
      "word": "folder",
      "similarity": 0.43447055,
      "clue": "weak connection",
      "strength": "weak"
    },
    {
      "rank": 367,
      "word": "limby",
      "similarity": 0.43230723,
      "clue": "weak connection",
      "strength": "weak"
    },
    {
      "rank": 368,
      "word": "forth",
      "similarity": 0.43188433,
      "clue": "weak connection",
      "strength": "weak"
    },
    {
      "rank": 370,
      "word": "lander",
      "similarity": 0.43147387,
      "clue": "weak connection",
      "strength": "weak"
    },
    {
      "rank": 371,
      "word": "fjeld",
      "similarity": 0.43120403,
      "clue": "weak connection",
      "strength": "weak"
    },
    {
      "rank": 380,
      "word": "fork",
      "similarity": 0.4283895,
      "clue": "weak connection",
      "strength": "weak"
    },
    {
      "rank": 389,
      "word": "folio",
      "similarity": 0.42599766,
      "clue": "weak connection",
      "strength": "weak"
    },
    {
      "rank": 393,
      "word": "fiction",
      "similarity": 0.42518365,
      "clue": "weak connection",
      "strength": "weak"
    },
    {
      "rank": 395,
      "word": "factory",
      "similarity": 0.42488365,
      "clue": "weak connection",
      "strength": "weak"
    },
    {
      "rank": 400,
      "word": "fabric",
      "similarity": 0.42330458,
      "clue": "weak connection",
      "strength": "weak"
    },
    {
      "rank": 403,
      "word": "greenheart",
      "similarity": 0.42250467,
      "clue": "weak connection",
      "strength": "weak"
    },
    {
      "rank": 408,
      "word": "sylvae",
      "similarity": 0.4211256,
      "clue": "weak connection",
      "strength": "weak"
    },
    {
      "rank": 410,
      "word": "safari",
      "similarity": 0.41980051,
      "clue": "weak connection",
      "strength": "weak"
    },
    {
      "rank": 411,
      "word": "heathland",
      "similarity": 0.41961932,
      "clue": "weak connection",
      "strength": "weak"
    },
    {
      "rank": 413,
      "word": "campo",
      "similarity": 0.41859269,
      "clue": "weak connection",
      "strength": "weak"
    },
    {
      "rank": 419,
      "word": "firm",
      "similarity": 0.41648043,
      "clue": "weak connection",
      "strength": "weak"
    },
    {
      "rank": 427,
      "word": "forestage",
      "similarity": 0.4137553,
      "clue": "weak connection",
      "strength": "weak"
    },
    {
      "rank": 433,
      "word": "woald",
      "similarity": 0.41186819,
      "clue": "weak connection",
      "strength": "weak"
    },
    {
      "rank": 437,
      "word": "vegetational",
      "similarity": 0.41097708,
      "clue": "weak connection",
      "strength": "weak"
    },
    {
      "rank": 439,
      "word": "wand",
      "similarity": 0.41062779,
      "clue": "weak connection",
      "strength": "weak"
    },
    {
      "rank": 440,
      "word": "oasis",
      "similarity": 0.41052131,
      "clue": "weak connection",
      "strength": "weak"
    },
    {
      "rank": 454,
      "word": "texture",
      "similarity": 0.40884298,
      "clue": "weak connection",
      "strength": "weak"
    },
    {
      "rank": 456,
      "word": "lore",
      "similarity": 0.40825024,
      "clue": "weak connection",
      "strength": "weak"
    },
    {
      "rank": 458,
      "word": "vinery",
      "similarity": 0.40765703,
      "clue": "weak connection",
      "strength": "weak"
    },
    {
      "rank": 459,
      "word": "fjord",
      "similarity": 0.40740551,
      "clue": "weak connection",
      "strength": "weak"
    },
    {
      "rank": 461,
      "word": "vineyard",
      "similarity": 0.40715135,
      "clue": "weak connection",
      "strength": "weak"
    },
    {
      "rank": 463,
      "word": "fossa",
      "similarity": 0.40659769,
      "clue": "weak connection",
      "strength": "weak"
    },
    {
      "rank": 466,
      "word": "bluewood",
      "similarity": 0.40626887,
      "clue": "weak connection",
      "strength": "weak"
    },
    {
      "rank": 469,
      "word": "milkwood",
      "similarity": 0.40568253,
      "clue": "weak connection",
      "strength": "weak"
    },
    {
      "rank": 472,
      "word": "fogbow",
      "similarity": 0.40548099,
      "clue": "weak connection",
      "strength": "weak"
    },
    {
      "rank": 475,
      "word": "avian",
      "similarity": 0.40492908,
      "clue": "weak connection",
      "strength": "weak"
    },
    {
      "rank": 480,
      "word": "arf",
      "similarity": 0.4046021,
      "clue": "weak connection",
      "strength": "weak"
    },
    {
      "rank": 488,
      "word": "tern",
      "similarity": 0.40309486,
      "clue": "weak connection",
      "strength": "weak"
    },
    {
      "rank": 491,
      "word": "estival",
      "similarity": 0.40235618,
      "clue": "weak connection",
      "strength": "weak"
    },
    {
      "rank": 492,
      "word": "berg",
      "similarity": 0.40233953,
      "clue": "weak connection",
      "strength": "weak"
    },
    {
      "rank": 494,
      "word": "film",
      "similarity": 0.40181686,
      "clue": "weak connection",
      "strength": "weak"
    },
    {
      "rank": 496,
      "word": "forecast",
      "similarity": 0.401788,
      "clue": "weak connection",
      "strength": "weak"
    },
    {
      "rank": 500,
      "word": "fantasy",
      "similarity": 0.40063375,
      "clue": "weak connection",
      "strength": "weak"
    },
    {
      "rank": 501,
      "word": "shelf",
      "similarity": 0.40051454,
      "clue": "weak connection",
      "strength": "weak"
    },
    {
      "rank": 505,
      "word": "stime",
      "similarity": 0.39951178,
      "clue": "weak connection",
      "strength": "weak"
    },
    {
      "rank": 510,
      "word": "zoo",
      "similarity": 0.39872672,
      "clue": "weak connection",
      "strength": "weak"
    },
    {
      "rank": 554,
      "word": "framework",
      "similarity": 0.39247561,
      "clue": "weak connection",
      "strength": "weak"
    },
    {
      "rank": 560,
      "word": "grid",
      "similarity": 0.39135998,
      "clue": "weak connection",
      "strength": "weak"
    },
    {
      "rank": 562,
      "word": "regreen",
      "similarity": 0.39126451,
      "clue": "weak connection",
      "strength": "weak"
    },
    {
      "rank": 573,
      "word": "finder",
      "similarity": 0.38983029,
      "clue": "weak connection",
      "strength": "weak"
    },
    {
      "rank": 577,
      "word": "west",
      "similarity": 0.38922143,
      "clue": "weak connection",
      "strength": "weak"
    },
    {
      "rank": 579,
      "word": "north",
      "similarity": 0.38892092,
      "clue": "weak connection",
      "strength": "weak"
    },
    {
      "rank": 585,
      "word": "loof",
      "similarity": 0.38844529,
      "clue": "weak connection",
      "strength": "weak"
    },
    {
      "rank": 589,
      "word": "foy",
      "similarity": 0.38791614,
      "clue": "weak connection",
      "strength": "weak"
    },
    {
      "rank": 590,
      "word": "aland",
      "similarity": 0.38780271,
      "clue": "weak connection",
      "strength": "weak"
    },
    {
      "rank": 597,
      "word": "decor",
      "similarity": 0.38683648,
      "clue": "weak connection",
      "strength": "weak"
    },
    {
      "rank": 605,
      "word": "fogger",
      "similarity": 0.38597852,
      "clue": "weak connection",
      "strength": "weak"
    },
    {
      "rank": 608,
      "word": "yardwand",
      "similarity": 0.38555934,
      "clue": "weak connection",
      "strength": "weak"
    },
    {
      "rank": 617,
      "word": "cornfield",
      "similarity": 0.38476356,
      "clue": "weak connection",
      "strength": "weak"
    },
    {
      "rank": 621,
      "word": "veal",
      "similarity": 0.38383056,
      "clue": "weak connection",
      "strength": "weak"
    },
    {
      "rank": 623,
      "word": "ender",
      "similarity": 0.38318389,
      "clue": "weak connection",
      "strength": "weak"
    },
    {
      "rank": 626,
      "word": "loom",
      "similarity": 0.38303979,
      "clue": "weak connection",
      "strength": "weak"
    },
    {
      "rank": 657,
      "word": "arcadia",
      "similarity": 0.37992785,
      "clue": "weak connection",
      "strength": "weak"
    },
    {
      "rank": 664,
      "word": "jaborandis",
      "similarity": 0.37897661,
      "clue": "weak connection",
      "strength": "weak"
    },
    {
      "rank": 671,
      "word": "sprucer",
      "similarity": 0.37829219,
      "clue": "weak connection",
      "strength": "weak"
    },
    {
      "rank": 679,
      "word": "rink",
      "similarity": 0.37756373,
      "clue": "weak connection",
      "strength": "weak"
    },
    {
      "rank": 680,
      "word": "fairy",
      "similarity": 0.37756243,
      "clue": "weak connection",
      "strength": "weak"
    },
    {
      "rank": 683,
      "word": "foin",
      "similarity": 0.37737089,
      "clue": "weak connection",
      "strength": "weak"
    },
    {
      "rank": 688,
      "word": "savine",
      "similarity": 0.37696039,
      "clue": "weak connection",
      "strength": "weak"
    },
    {
      "rank": 693,
      "word": "geobotanic",
      "similarity": 0.37639143,
      "clue": "weak connection",
      "strength": "weak"
    },
    {
      "rank": 708,
      "word": "landscapist",
      "similarity": 0.37543937,
      "clue": "weak connection",
      "strength": "weak"
    },
    {
      "rank": 718,
      "word": "touchwood",
      "similarity": 0.37436607,
      "clue": "weak connection",
      "strength": "weak"
    },
    {
      "rank": 727,
      "word": "outdoor",
      "similarity": 0.37346375,
      "clue": "weak connection",
      "strength": "weak"
    },
    {
      "rank": 733,
      "word": "vest",
      "similarity": 0.3729556,
      "clue": "weak connection",
      "strength": "weak"
    },
    {
      "rank": 737,
      "word": "forcer",
      "similarity": 0.37253586,
      "clue": "weak connection",
      "strength": "weak"
    },
    {
      "rank": 738,
      "word": "future",
      "similarity": 0.37250905,
      "clue": "weak connection",
      "strength": "weak"
    },
    {
      "rank": 740,
      "word": "faerie",
      "similarity": 0.37243098,
      "clue": "weak connection",
      "strength": "weak"
    },
    {
      "rank": 746,
      "word": "wall",
      "similarity": 0.37218784,
      "clue": "weak connection",
      "strength": "weak"
    },
    {
      "rank": 754,
      "word": "ecofreak",
      "similarity": 0.37139561,
      "clue": "weak connection",
      "strength": "weak"
    },
    {
      "rank": 767,
      "word": "indow",
      "similarity": 0.37062245,
      "clue": "weak connection",
      "strength": "weak"
    },
    {
      "rank": 777,
      "word": "dreamland",
      "similarity": 0.3692548,
      "clue": "weak connection",
      "strength": "weak"
    },
    {
      "rank": 790,
      "word": "creasing",
      "similarity": 0.36841272,
      "clue": "weak connection",
      "strength": "weak"
    },
    {
      "rank": 800,
      "word": "retched",
      "similarity": 0.36788686,
      "clue": "weak connection",
      "strength": "weak"
    },
    {
      "rank": 812,
      "word": "visor",
      "similarity": 0.36698206,
      "clue": "weak connection",
      "strength": "weak"
    },
    {
      "rank": 817,
      "word": "coal",
      "similarity": 0.3664714,
      "clue": "weak connection",
      "strength": "weak"
    },
    {
      "rank": 829,
      "word": "defog",
      "similarity": 0.36575443,
      "clue": "weak connection",
      "strength": "weak"
    },
    {
      "rank": 833,
      "word": "fuji",
      "similarity": 0.36563737,
      "clue": "weak connection",
      "strength": "weak"
    },
    {
      "rank": 835,
      "word": "far",
      "similarity": 0.36560003,
      "clue": "weak connection",
      "strength": "weak"
    },
    {
      "rank": 838,
      "word": "horizon",
      "similarity": 0.36540688,
      "clue": "weak connection",
      "strength": "weak"
    },
    {
      "rank": 842,
      "word": "deck",
      "similarity": 0.36530053,
      "clue": "weak connection",
      "strength": "weak"
    },
    {
      "rank": 843,
      "word": "trap",
      "similarity": 0.36529605,
      "clue": "weak connection",
      "strength": "weak"
    },
    {
      "rank": 844,
      "word": "fantasm",
      "similarity": 0.36529382,
      "clue": "weak connection",
      "strength": "weak"
    },
    {
      "rank": 846,
      "word": "triforia",
      "similarity": 0.36504733,
      "clue": "weak connection",
      "strength": "weak"
    },
    {
      "rank": 857,
      "word": "scenario",
      "similarity": 0.36448693,
      "clue": "weak connection",
      "strength": "weak"
    },
    {
      "rank": 860,
      "word": "frowst",
      "similarity": 0.36439545,
      "clue": "weak connection",
      "strength": "weak"
    },
    {
      "rank": 862,
      "word": "barn",
      "similarity": 0.36431902,
      "clue": "weak connection",
      "strength": "weak"
    },
    {
      "rank": 863,
      "word": "wonderland",
      "similarity": 0.36425048,
      "clue": "weak connection",
      "strength": "weak"
    },
    {
      "rank": 864,
      "word": "oft",
      "similarity": 0.36421787,
      "clue": "weak connection",
      "strength": "weak"
    },
    {
      "rank": 871,
      "word": "wynd",
      "similarity": 0.36400507,
      "clue": "weak connection",
      "strength": "weak"
    },
    {
      "rank": 872,
      "word": "directory",
      "similarity": 0.36399755,
      "clue": "weak connection",
      "strength": "weak"
    },
    {
      "rank": 874,
      "word": "swith",
      "similarity": 0.36391953,
      "clue": "weak connection",
      "strength": "weak"
    },
    {
      "rank": 877,
      "word": "villa",
      "similarity": 0.36384274,
      "clue": "weak connection",
      "strength": "weak"
    },
    {
      "rank": 883,
      "word": "fozy",
      "similarity": 0.36344925,
      "clue": "weak connection",
      "strength": "weak"
    },
    {
      "rank": 889,
      "word": "district",
      "similarity": 0.3630645,
      "clue": "weak connection",
      "strength": "weak"
    },
    {
      "rank": 892,
      "word": "ness",
      "similarity": 0.36257071,
      "clue": "weak connection",
      "strength": "weak"
    },
    {
      "rank": 896,
      "word": "bushed",
      "similarity": 0.36228449,
      "clue": "weak connection",
      "strength": "weak"
    },
    {
      "rank": 899,
      "word": "mind",
      "similarity": 0.36223254,
      "clue": "weak connection",
      "strength": "weak"
    },
    {
      "rank": 901,
      "word": "vision",
      "similarity": 0.36202361,
      "clue": "weak connection",
      "strength": "weak"
    },
    {
      "rank": 904,
      "word": "althorn",
      "similarity": 0.36191862,
      "clue": "weak connection",
      "strength": "weak"
    },
    {
      "rank": 907,
      "word": "coastland",
      "similarity": 0.36176288,
      "clue": "weak connection",
      "strength": "weak"
    },
    {
      "rank": 911,
      "word": "foxlike",
      "similarity": 0.36157421,
      "clue": "weak connection",
      "strength": "weak"
    },
    {
      "rank": 914,
      "word": "cutbank",
      "similarity": 0.3613935,
      "clue": "weak connection",
      "strength": "weak"
    },
    {
      "rank": 917,
      "word": "trench",
      "similarity": 0.36130905,
      "clue": "weak connection",
      "strength": "weak"
    },
    {
      "rank": 920,
      "word": "coon",
      "similarity": 0.36120683,
      "clue": "weak connection",
      "strength": "weak"
    },
    {
      "rank": 921,
      "word": "fairway",
      "similarity": 0.36119881,
      "clue": "weak connection",
      "strength": "weak"
    },
    {
      "rank": 925,
      "word": "foh",
      "similarity": 0.3609446,
      "clue": "weak connection",
      "strength": "weak"
    },
    {
      "rank": 927,
      "word": "woodstove",
      "similarity": 0.36084895,
      "clue": "weak connection",
      "strength": "weak"
    },
    {
      "rank": 930,
      "word": "neath",
      "similarity": 0.36069291,
      "clue": "weak connection",
      "strength": "weak"
    },
    {
      "rank": 933,
      "word": "druid",
      "similarity": 0.36056116,
      "clue": "weak connection",
      "strength": "weak"
    },
    {
      "rank": 939,
      "word": "sandbox",
      "similarity": 0.36020648,
      "clue": "weak connection",
      "strength": "weak"
    },
    {
      "rank": 942,
      "word": "ambary",
      "similarity": 0.36013167,
      "clue": "weak connection",
      "strength": "weak"
    },
    {
      "rank": 943,
      "word": "cityscape",
      "similarity": 0.36011119,
      "clue": "weak connection",
      "strength": "weak"
    },
    {
      "rank": 944,
      "word": "fusain",
      "similarity": 0.36001744,
      "clue": "weak connection",
      "strength": "weak"
    },
    {
      "rank": 948,
      "word": "fantasia",
      "similarity": 0.35963223,
      "clue": "weak connection",
      "strength": "weak"
    },
    {
      "rank": 950,
      "word": "cloth",
      "similarity": 0.35961469,
      "clue": "weak connection",
      "strength": "weak"
    },
    {
      "rank": 954,
      "word": "felwort",
      "similarity": 0.35940218,
      "clue": "weak connection",
      "strength": "weak"
    },
    {
      "rank": 960,
      "word": "ream",
      "similarity": 0.35916503,
      "clue": "weak connection",
      "strength": "weak"
    },
    {
      "rank": 964,
      "word": "osier",
      "similarity": 0.35892845,
      "clue": "weak connection",
      "strength": "weak"
    },
    {
      "rank": 965,
      "word": "airn",
      "similarity": 0.35892634,
      "clue": "weak connection",
      "strength": "weak"
    },
    {
      "rank": 966,
      "word": "fantast",
      "similarity": 0.35891608,
      "clue": "weak connection",
      "strength": "weak"
    },
    {
      "rank": 967,
      "word": "brosy",
      "similarity": 0.35882818,
      "clue": "weak connection",
      "strength": "weak"
    },
    {
      "rank": 978,
      "word": "waitress",
      "similarity": 0.35843084,
      "clue": "weak connection",
      "strength": "weak"
    },
    {
      "rank": 979,
      "word": "thesis",
      "similarity": 0.3584298,
      "clue": "weak connection",
      "strength": "weak"
    },
    {
      "rank": 980,
      "word": "horste",
      "similarity": 0.35837228,
      "clue": "weak connection",
      "strength": "weak"
    },
    {
      "rank": 994,
      "word": "folia",
      "similarity": 0.35762062,
      "clue": "weak connection",
      "strength": "weak"
    },
    {
      "rank": 996,
      "word": "houseplant",
      "similarity": 0.35757441,
      "clue": "weak connection",
      "strength": "weak"
    },
    {
      "rank": 1000,
      "word": "tain",
      "similarity": 0.35750492,
      "clue": "weak connection",
      "strength": "weak"
    },
    {
      "rank": 1004,
      "word": "clear",
      "similarity": 0.35736175,
      "clue": "weak connection",
      "strength": "weak"
    },
    {
      "rank": 1005,
      "word": "cape",
      "similarity": 0.35723489,
      "clue": "weak connection",
      "strength": "weak"
    },
    {
      "rank": 1007,
      "word": "fossick",
      "similarity": 0.35714865,
      "clue": "weak connection",
      "strength": "weak"
    },
    {
      "rank": 1008,
      "word": "virid",
      "similarity": 0.35710815,
      "clue": "weak connection",
      "strength": "weak"
    },
    {
      "rank": 1009,
      "word": "context",
      "similarity": 0.35709482,
      "clue": "weak connection",
      "strength": "weak"
    },
    {
      "rank": 1011,
      "word": "arborize",
      "similarity": 0.35706137,
      "clue": "weak connection",
      "strength": "weak"
    },
    {
      "rank": 1018,
      "word": "duneland",
      "similarity": 0.35675417,
      "clue": "weak connection",
      "strength": "weak"
    },
    {
      "rank": 1019,
      "word": "found",
      "similarity": 0.35675348,
      "clue": "weak connection",
      "strength": "weak"
    },
    {
      "rank": 1021,
      "word": "emerald",
      "similarity": 0.35664475,
      "clue": "weak connection",
      "strength": "weak"
    },
    {
      "rank": 1022,
      "word": "ague",
      "similarity": 0.35639283,
      "clue": "weak connection",
      "strength": "weak"
    },
    {
      "rank": 1024,
      "word": "froggiest",
      "similarity": 0.3562756,
      "clue": "weak connection",
      "strength": "weak"
    },
    {
      "rank": 1026,
      "word": "parka",
      "similarity": 0.35619749,
      "clue": "weak connection",
      "strength": "weak"
    },
    {
      "rank": 1027,
      "word": "furry",
      "similarity": 0.35610055,
      "clue": "weak connection",
      "strength": "weak"
    },
    {
      "rank": 1028,
      "word": "minefield",
      "similarity": 0.35608002,
      "clue": "weak connection",
      "strength": "weak"
    },
    {
      "rank": 1029,
      "word": "forum",
      "similarity": 0.35601907,
      "clue": "weak connection",
      "strength": "weak"
    }
  ],
  "total_count": 157
}